bdp/__init__.py
bdp/api.py
bdp/test.py
BDPapi-0.1.0.dist-info/LICENSE
BDPapi-0.1.0.dist-info/METADATA
BDPapi-0.1.0.dist-info/WHEEL
BDPapi-0.1.0.dist-info/top_level.txt
BDPapi-0.1.0.dist-info/RECORD
